fun_dist/__init__.py
fun_dist/classes.py
fun_dist/distances.py
fun_dist/ellipse.py
fun_dist/rotate.py
fun_dist/tangent.py
fun_dist-0.0.4b0.dist-info/METADATA
fun_dist-0.0.4b0.dist-info/WHEEL
fun_dist-0.0.4b0.dist-info/top_level.txt
fun_dist-0.0.4b0.dist-info/RECORD
