Metadata-Version: 2.1
Name: fun-dist
Version: 0.0.4b0
Summary: A python package, that provides functions for calculating distances and finding tangents of math functions
Home-page: https://github.com/EgorVoron/fun_dist
Author: Egor Voron
Author-email: ekvoron01@gmail.com
License: UNKNOWN
Platform: UNKNOWN
Classifier: Programming Language :: Python :: 3
Classifier: License :: OSI Approved :: MIT License
Requires-Python: >=3.6
